[
  {
    "title": "بياتريس كولومينا: فيليب جونسون على شاشة التلفاز",
    "url": "/node0001.html",
    "content": "تلفازٌ وبيتٌ من الزجاج الخالص، حُلمان مُلحّان من أحلام القرن العشرين، شاءت الأقدار أن يتحققا معاً في ذات البقعة والحقبة: الريف الأميركي أواسط القرن العشرين. طوال القرن التاسع عشر ستخلب تجارب وخيالات الزجاج ألباب كتاب الخيال العلمي، كما ستطبع ذائقة المعماريين الحداثيين على السواء. إلا أن هذه التجارب والخيالات لن تكون قابلة للسكن قبل انتصاف القرن العشرين مع بيت فارنزورث لميز فان دير روهه في بلانو بولاية إلينوي وبيت الزجاج لفيليب جونسون في نيو كانن بولاية كنيتيكت. كحوامة فضائية حطّت لتوها، يطفو بيت فارنزورث فوق سطح الأرض بقليل، بينما يربض بيت الزجاج على مرسىً صلب يبدو حيناً كبساط سحري، وحيناً كـ طوف عائم بحد وصف جونسون. "
  },
  {
    "title": "بنجامن براتون: المنظومة: عن البرمجيات والسيادة",
    "url": "/node0005.html",
    "content": "في خطابها أمام مجلس العلاقات الخارجية عن الحاجة لتصميمٍ جديدٍ للنظام الجيوسياسي العالمي، قدّمت هلاري كلنتون، وزيرة الخارجية الأميركية آنذاك، اقتراحاً صادماً بعض الشيء. تحدثّت كلنتون عن عمارةٍ جديدةٍ لهذا العالم الجديد؛ لا تشبه المعابد الإغريقية القديمة، بل هي أقرب إلى بنايات فرانك غيري. في مقابل بنايات غيري شديدة التعقيد والغرابة، وصفت كلنتون النظام العالمي الحالي الذي تؤطره الأمم المتحدة وحلف الناتو وعدد من المنظمات الدولية الكبرى بمعبد أثيني كلاسيكي، بسيط الترتيب وواضح البنية. تقول كلنتون في الماضي أمكن لعددٍ من الأعمدة القوية أن تحمل ثقل العالم ومشاكله، أمّا الآن، يحتاج الأمر إلى توليفة ديناميكية من التراكيب والمواد. ثم تردف بعض من أعماله تقصد فرانك غيري تبدو عشوائية وطارئة في بادئ الأمر، إلا أنها في واقع الحال على درجة عالية من التخطيط والتعقيد."
  }
]